digilab/__init__.py
digilab/aws.py
digilab-0.0.0.dist-info/METADATA
digilab-0.0.0.dist-info/WHEEL
digilab-0.0.0.dist-info/RECORD
