Metadata-Version: 2.1
Name: digilab
Version: 0.0.0
Summary: digiLab public API
Author: FreddyWordingham
Author-email: freddy@digilab.co.uk
Requires-Python: >=3.9,<4.0
Classifier: Programming Language :: Python :: 3
Classifier: Programming Language :: Python :: 3.9
Classifier: Programming Language :: Python :: 3.10
Classifier: Programming Language :: Python :: 3.11
